<?xml version="1.0" ?>
<!DOCTYPE change_log SYSTEM "changes.dtd" >


<change_log title="nginx-quic">


<changes apply="nginx-quic" ver="1.23.4" rev="0.20230124"
         date="2023-01-24" time="18:18:30 -0800"
         packager="Nginx Packaging &lt;nginx-packaging@f5.com&gt;">
<change>
<para>
Updated to 1.23.4-0.20230124 (nginx-quic a954b551dc3f)
</para>
</change>

</changes>


<changes apply="nginx-quic" ver="1.23.3" rev="1"
         date="2023-01-10" time="12:00:00 -0000"
         packager="Nginx Packaging &lt;nginx-packaging@f5.com&gt;">
<change>
<para>
Initial release based on 1.23.3
</para>
</change>

</changes>

</change_log>
